scrapy_nodriver/__init__.py
scrapy_nodriver/_utils.py
scrapy_nodriver/handler.py
scrapy_nodriver/page.py
scrapy_nodriver-0.0.7.dist-info/METADATA
scrapy_nodriver-0.0.7.dist-info/WHEEL
scrapy_nodriver-0.0.7.dist-info/RECORD
